{
  "Green Mile": {
    "Cast": {
      "Bonney Hunt": "Janise Edgecomb",
      "David Mors": "Brut <Brute> Howell",
      "James Cromwell": "Hall Murse",
      "Mikle Clark Duncan": "John Koffie",
      "Tom Hanks": "Paul Edgecomb"
    },
    "Company": "Warner Brothers",
    "Country": "USA",
    "Director": [
      "Frank Darabont"
    ],
    "Producer": [
      "Frank Darabont",
      "David Valdes"
    ],
    "Screenwriter": [
      "Frank Darabont",
      "Stephen King"
    ],
    "Title": "Green Mile",
    "Year": 1999
  }
}
{
  "The Terminal": {
    "Cast": {
      "Catrine Zeta-Jhones": "Amelia Warren",
      "Konrad Pla": "Officer",
      "Mark Ivanir": "Taxi-driver Horan",
      "Mikle Noori": "Maks",
      "Tom Hanks": "Victor Navorski"
    },
    "Company": "NONE",
    "Country": "USA",
    "Director": [
      "Stephen Spielberg"
    ],
    "Producer": [
      "Lory Mc.Donald",
      "Walter F. Parks",
      "Stephen Spielberg"
    ],
    "Screenwriter": [
      "Jeff Natanson",
      "Andry Nikkol",
      "Sasha Jervacy"
    ],
    "Title": "The Terminal",
    "Year": 2004
  }
}
{
  "Forrest Gamp": {
    "Cast": {
      "Hary Sinise": "lieutenant Den Taylor",
      "Robin Right": "Jenny Carren",
      "Sally Field": "Mrs.Gamp",
      "Sam Anderson": "Director Hankok",
      "Tom Hanks": "Forrest Gamp"
    },
    "Company": "NONE",
    "Country": "USA",
    "Director": [
      "Robert Zemekis"
    ],
    "Producer": [
      "Wandy Finerman",
      "Steave Starkie",
      "Steave Teesh"
    ],
    "Screenwriter": [
      "Erik Rot",
      "Winston Groome"
    ],
    "Title": "Forrest Gamp",
    "Year": 1994
  }
}
